easyntp/__init__.py
easyntp-1.0.0.dist-info/METADATA
easyntp-1.0.0.dist-info/WHEEL
easyntp-1.0.0.dist-info/top_level.txt
easyntp-1.0.0.dist-info/RECORD
