Metadata-Version: 2.1
Name: easyntp
Version: 1.0.0
Summary: Easy NTP library
Home-page: https://github.com/lang-library/py-easyntp
Author: JavaCommons Technologies
Author-email: javacommmons@gmail.com
License: MIT
Classifier: Programming Language :: Python
Classifier: Programming Language :: Python :: 3
Classifier: Programming Language :: Python :: 3.4
Classifier: Programming Language :: Python :: 3.5
Classifier: Programming Language :: Python :: 3.6
Requires-Dist: ntplib
